explainaboard_api_client/__init__.py
explainaboard_api_client/api_client.py
explainaboard_api_client/configuration.py
explainaboard_api_client/exceptions.py
explainaboard_api_client/model_utils.py
explainaboard_api_client/rest.py
explainaboard_api_client/api/__init__.py
explainaboard_api_client/api/default_api.py
explainaboard_api_client/apis/__init__.py
explainaboard_api_client/model/__init__.py
explainaboard_api_client/model/analysis.py
explainaboard_api_client/model/analysis_case.py
explainaboard_api_client/model/analysis_level.py
explainaboard_api_client/model/analysis_result.py
explainaboard_api_client/model/any_type.py
explainaboard_api_client/model/api_error.py
explainaboard_api_client/model/api_systems_analyses_feature_to_bucket_info.py
explainaboard_api_client/model/benchmark.py
explainaboard_api_client/model/benchmark_config.py
explainaboard_api_client/model/benchmark_config_all_of.py
explainaboard_api_client/model/benchmark_create_props.py
explainaboard_api_client/model/benchmark_dataset_config.py
explainaboard_api_client/model/benchmark_metric.py
explainaboard_api_client/model/benchmark_operation_config.py
explainaboard_api_client/model/benchmark_table_data.py
explainaboard_api_client/model/benchmark_update_props.py
explainaboard_api_client/model/benchmark_view_config.py
explainaboard_api_client/model/class_label.py
explainaboard_api_client/model/combo_count.py
explainaboard_api_client/model/confidence_interval.py
explainaboard_api_client/model/dataset_feature.py
explainaboard_api_client/model/dataset_metadata.py
explainaboard_api_client/model/datasets_return.py
explainaboard_api_client/model/feature_type.py
explainaboard_api_client/model/inline_object.py
explainaboard_api_client/model/inline_response200.py
explainaboard_api_client/model/language_code.py
explainaboard_api_client/model/metric_result.py
explainaboard_api_client/model/metric_result_values.py
explainaboard_api_client/model/paper.py
explainaboard_api_client/model/score.py
explainaboard_api_client-0.4.3.dist-info/METADATA
explainaboard_api_client-0.4.3.dist-info/WHEEL
explainaboard_api_client-0.4.3.dist-info/top_level.txt
explainaboard_api_client-0.4.3.dist-info/RECORD
