Metadata-Version: 2.1
Name: explainaboard-api-client
Version: 0.4.3
Summary: ExplainaBoard
Home-page: UNKNOWN
Author: OpenAPI Generator community
Author-email: team@openapitools.org
License: MIT License
Keywords: OpenAPI,OpenAPI-Generator,ExplainaBoard
Platform: UNKNOWN
Requires-Python: >=3.6
Requires-Dist: urllib3 (>=1.25.3)
Requires-Dist: python-dateutil
